[
    {
        "id":"ca-app-pub-2334640401367012/9314717422",
        "is_show": true,
        "position": "home_native"
    },
    {
        "id":"ca-app-pub-2334640401367012/9314717422",
        "is_show": true,
        "position": "adult_list_native"
    },
    {
        "id":"ca-app-pub-2334640401367012/9314717422",
        "is_show": true,
        "position": "adult_category_native"
    },
    {
        "id":"ca-app-pub-2334640401367012/9314717422",
        "is_show": true,
        "position": "baby_list_native"
    },
    {
        "id":"ca-app-pub-2334640401367012/9314717422",
        "is_show": true,
        "position": "baby_category_native"
    },
    {
        "id":"ca-app-pub-2334640401367012/9314717422",
        "is_show": true,
        "position": "collection_native"
    },
    {
        "id":"ca-app-pub-2334640401367012/3189999066",
        "is_show": true,
        "position": "player_native"
    },
    {
        "id":"ca-app-pub-2334640401367012/8151515853",
        "is_show": true,
        "position": "app_open_hot"
    },
    {
        "id":"ca-app-pub-2334640401367012/8151515853",
        "is_show": true,
        "position": "app_open_cold"
    },
    {
        "id":"ca-app-pub-2334640401367012/7529457495",
        "is_show": true,
        "position": "player_insert"
    },
    {
        "id":"ca-app-pub-2334640401367012/7529457495",
        "is_show": true,
        "position": "adult_category_insert"
    },
    {
        "id":"ca-app-pub-2334640401367012/7529457495",
        "is_show": true,
        "position": "baby_category_insert"
    },
    {
        "id":"ca-app-pub-2334640401367012/7529457495",
        "is_show": true,
        "position": "baby_list_insert"
    },
    {
        "id":"ca-app-pub-2334640401367012/7529457495",
        "is_show": true,
        "position": "adult_list_insert"
    },
    {
        "id":"ca-app-pub-2334640401367012/7529457495",
        "is_show": true,
        "position": "history_insert"
    },
    {
        "id":"ca-app-pub-2334640401367012/7529457495",
        "is_show": true,
        "position": "random_insert"
    },
    {
        "id":"ca-app-pub-2334640401367012/7529457495",
        "is_show": true,
        "position": "paywall_insert"
    },
    {
        "id":"ca-app-pub-2334640401367012/7529457495",
        "is_show": true,
        "position": "back_insert"
    }
]
